DatabaseLibrary/VERSION
DatabaseLibrary/__init__.py
DatabaseLibrary/assertion.py
DatabaseLibrary/connection_manager.py
DatabaseLibrary/query.py
robotframework_databaseslibrary-0.8.10.dist-info/DESCRIPTION.rst
robotframework_databaseslibrary-0.8.10.dist-info/METADATA
robotframework_databaseslibrary-0.8.10.dist-info/RECORD
robotframework_databaseslibrary-0.8.10.dist-info/WHEEL
robotframework_databaseslibrary-0.8.10.dist-info/metadata.json
robotframework_databaseslibrary-0.8.10.dist-info/top_level.txt
