Metadata-Version: 2.0
Name: robotframework-databaseslibrary
Version: 0.8.10
Summary: Database utility library for Robot Framework
Home-page: https://github.com/qitaos/Robotframework-Database-Library/
Author: qitaos
Author-email: qitaos@gmail.com
License: UNKNOWN
Platform: UNKNOWN
Requires: robotframework
